filesender/__init__.py
filesender/filesender.py
filesender/copy_script/FTP.py
filesender/copy_script/Scripter.py
filesender/copy_script/VBScript.py
filesender/copy_script/Wget.py
filesender/copy_script/__init__.py
filesender/copy_script/hex.py
filesender/copy_script/powershell.py
filesender/server/FTP.py
filesender/server/HTTP.py
filesender/server/__init__.py
filesender-1.2.1.dist-info/LICENSE
filesender-1.2.1.dist-info/METADATA
filesender-1.2.1.dist-info/WHEEL
filesender-1.2.1.dist-info/entry_points.txt
filesender-1.2.1.dist-info/top_level.txt
filesender-1.2.1.dist-info/RECORD
