Metadata-Version: 2.1
Name: filesender
Version: 1.2.1
Summary: Create script into different language to download a file form a server . Can be useful to send file via a SQLi. 
Home-page: https://github.com/EmilienPer/FileSender
Author: Emilien Peretti
Author-email: code@emilienperetti.be
License: AGPLv3
Platform: UNKNOWN
Requires-Dist: requests
Requires-Dist: pyftpdlib
